karnak/fetcher/karnak_sqs_fetcher.py
karnak/fetcher/sqs_fetcher.py
karnak/util/argparse.py
karnak/util/athena.py
karnak/util/db.py
karnak/util/log.py
karnak/util/path.py
karnak/util/profiling.py
karnak/util/redshift.py
karnak/util/aws/sqs.py
karnak-3.5.0.dist-info/licenses/LICENSE
karnak3/cloud/__init__.py
karnak3/cloud/aws/__init__.py
karnak3/cloud/aws/athena.py
karnak3/cloud/aws/s3.py
karnak3/cloud/aws/sqs.py
karnak3/cloud/aws/ssm.py
karnak3/cloud/aws/sts.py
karnak3/cloud/aws/redshift/__init__.py
karnak3/cloud/aws/redshift/legacy.py
karnak3/core/arg.py
karnak3/core/config.py
karnak3/core/dataframe.py
karnak3/core/engine_registry.py
karnak3/core/profiling.py
karnak3/core/time_window.py
karnak3/core/db/__init__.py
karnak3/core/log/__init__.py
karnak3/core/log/legacy.py
karnak3/core/store/__init__.py
karnak3/core/store/file.py
karnak3/core/util/__init__.py
karnak3/core/util/collections.py
karnak3/core/util/compression.py
karnak3/core/util/datetime.py
karnak3/core/util/decorators.py
karnak3/core/util/inspect.py
karnak3/core/util/numeric.py
karnak3/core/util/pandas.py
karnak3/core/util/path.py
karnak3/core/util/string.py
karnak3/core/util/tempfile.py
karnak3/fetch/base_fetcher.py
karnak3/fetch/sqs_fetcher.py
test/integration/util/athena/run_athena_select.py
test/unit/karnak3/core/arg.py
test/unit/karnak3/core/test_log.py
test/unit/karnak3/core/test_time_window.py
test/unit/karnak3/core/util/test_datetime.py
test/unit/karnak3/core/util/test_path.py
karnak-3.5.0.dist-info/METADATA
karnak-3.5.0.dist-info/WHEEL
karnak-3.5.0.dist-info/top_level.txt
karnak-3.5.0.dist-info/RECORD
